README.md
setup.py
putdig/__init__.py
putdig/common/__init__.py
putdig/common/discovery.py
putdig/common/types.py
putdig/common/utils.py
putdig_common.egg-info/PKG-INFO
putdig_common.egg-info/SOURCES.txt
putdig_common.egg-info/dependency_links.txt
putdig_common.egg-info/requires.txt
putdig_common.egg-info/top_level.txt