Metadata-Version: 2.1
Name: putdig-common
Version: 0.2.0
Summary: Common interface and business logic for PuTDIG and PuTDIG-CLI
Home-page: https://github.com/PumpkinSpace/PuTDIG-Common
Author: James Womack, Jack Hughes
Author-email: info@pumpkininc.com
License: UNKNOWN
Platform: UNKNOWN
Classifier: Programming Language :: Python :: 3
Classifier: License :: OSI Approved :: MIT License
Classifier: Operating System :: OS Independent
Requires-Python: >=3.7
